{"slug":"/cn/1155","title":"吴越春秋 - (东汉)赵晔","child":[{"slug":"/cn/1155/1","title":"吴太伯传第一","open":true},{"slug":"/cn/1155/2","title":"吴王寿梦传第二","open":true},{"slug":"/cn/1155/3","title":"王僚使公子光传第三","open":true},{"slug":"/cn/1155/4","title":"阖闾内传第四","open":true},{"slug":"/cn/1155/5","title":"夫差内传第五","open":true},{"slug":"/cn/1155/6","title":"越王无余外传第六","open":true},{"slug":"/cn/1155/7","title":"勾践入臣外传第七","open":true},{"slug":"/cn/1155/8","title":"勾践归国外传第八","open":true},{"slug":"/cn/1155/9","title":"勾践阴谋外传第九","open":true},{"slug":"/cn/1155/10","title":"勾践伐吴外传第十","open":true}]}