{"slug":"/cn/734","title":"洗脑的历史 - 傅志彬","child":[{"slug":"/cn/734/1","title":"第一章","open":true},{"slug":"/cn/734/2","title":"第二章","open":true},{"slug":"/cn/734/3","title":"第三章","open":true},{"slug":"/cn/734/4","title":"第四章","open":true},{"slug":"/cn/734/5","title":"第五章","open":true},{"slug":"/cn/734/6","title":"第六章","open":true},{"slug":"/cn/734/7","title":"第七章","open":true},{"slug":"/cn/734/8","title":"第八章","open":true},{"slug":"/cn/734/9","title":"第九章","open":true},{"slug":"/cn/734/10","title":"第十章","open":true}]}