{"slug":"/yi/285","title":"猫头鹰在黄昏起飞(川上未映子 村上春树) - 林少华译","child":[{"slug":"/yi/285/1","title":"第一章　优秀的鼓手不击打最关键的音","open":true,"child":[{"slug":"/yi/285/1/1","title":"朗读会的回忆"},{"slug":"/yi/285/1/2","title":"“诉说”的变化"},{"slug":"/yi/285/1/3","title":"文件柜的存在"},{"slug":"/yi/285/1/4","title":"关于“人称”"},{"slug":"/yi/285/1/5","title":"出场人物，不羁的灵魂们"},{"slug":"/yi/285/1/6","title":"真正的现实性是超越现实的东西"},{"slug":"/yi/285/1/7","title":"让故事“潜入”"},{"slug":"/yi/285/1/8","title":"文章的节奏，取决于修改"},{"slug":"/yi/285/1/9","title":"村上春树令人惊讶的“坦率”"},{"slug":"/yi/285/1/10","title":"关于中上健次的回忆"},{"slug":"/yi/285/1/11","title":"“脑袋沸腾”的时候"},{"slug":"/yi/285/1/12","title":"追求唯独自己才能做的事"},{"slug":"/yi/285/1/13","title":"始于和书相遇的奇迹"},{"slug":"/yi/285/1/14","title":"将来，爵士乐酒吧……"}]},{"slug":"/yi/285/2","title":"第二章　地下二层发生的事","open":true,"child":[{"slug":"/yi/285/2/1","title":"书名和人称如何确定"},{"slug":"/yi/285/2/2","title":"觉得“恶”的形式变了"},{"slug":"/yi/285/2/3","title":"下到地下室的危险"},{"slug":"/yi/285/2/4","title":"因为那是我的洞穴风格"},{"slug":"/yi/285/2/5","title":"我不是艺术家类型"},{"slug":"/yi/285/2/6","title":"要想“无计划”地写小说……"},{"slug":"/yi/285/2/7","title":"猫头鹰和作家的文件柜"},{"slug":"/yi/285/2/8","title":"引水员三十五六岁正好"},{"slug":"/yi/285/2/9","title":"信用交易，把时间拉向自己这边"},{"slug":"/yi/285/2/10","title":"地下一层的“闷闷不乐室”问题"},{"slug":"/yi/285/2/11","title":"“渥美清和寅次郎”可不好办"},{"slug":"/yi/285/2/12","title":"免色留下的谜"},{"slug":"/yi/285/2/13","title":"我的理念和那个无关"},{"slug":"/yi/285/2/14","title":"精神主义者同小说家的差异"},{"slug":"/yi/285/2/15","title":"但愿是积极的结尾"},{"slug":"/yi/285/2/16","title":"你本身因写作而有了变化吗？"}]},{"slug":"/yi/285/3","title":"第三章　失眠之夜和胖邮差同样罕见","open":true,"child":[{"slug":"/yi/285/3/1","title":"只要语句不断改变，就无需害怕"},{"slug":"/yi/285/3/2","title":"《挪威的森林》和虚幻脚本"},{"slug":"/yi/285/3/3","title":"真正追求的，可能不是男性吧"},{"slug":"/yi/285/3/4","title":"通过写作了解自己"},{"slug":"/yi/285/3/5","title":"不让读者入睡的两个秘诀"},{"slug":"/yi/285/3/6","title":"活法难教，写法也一样"},{"slug":"/yi/285/3/7","title":"文体是心灵之窗"},{"slug":"/yi/285/3/8","title":"拉手领去哪里的存在"},{"slug":"/yi/285/3/9","title":"女性是否过于承担性方面的职责"},{"slug":"/yi/285/3/10","title":"这样的女人，以前从未读过"},{"slug":"/yi/285/3/11","title":"触摸地下潜藏的自身影子的瞬间"}]},{"slug":"/yi/285/4","title":"第四章　即使没纸，人也不断讲述","open":true,"child":[{"slug":"/yi/285/4/1","title":"日记留不下，记录数字"},{"slug":"/yi/285/4/2","title":"先适当跳过不写即可"},{"slug":"/yi/285/4/3","title":"好像开始了新的第一人称世界"},{"slug":"/yi/285/4/4","title":"过去写的书老了，没办法重读"},{"slug":"/yi/285/4/5","title":"如同斯普林斯汀的自问"},{"slug":"/yi/285/4/6","title":"我不过负责产业链的生产罢了"},{"slug":"/yi/285/4/7","title":"死了会怎么样"},{"slug":"/yi/285/4/8","title":"语言是独自行走的东西"},{"slug":"/yi/285/4/9","title":"想比真正的炸牡蛎还更能刺激食欲"},{"slug":"/yi/285/4/10","title":"善的故事和远古洞穴相连"}]},{"slug":"/yi/285/5","title":"写在访谈后","open":true}]}