{"slug":"/cn/1153","title":"李云龙诗词全集 - (明清)","child":[{"slug":"/cn/1153/1","title":"五言律诗","child":[{"slug":"/cn/1153/1/1","title":"立秋夜"},{"slug":"/cn/1153/1/2","title":"秋日"},{"slug":"/cn/1153/1/3","title":"小楼"},{"slug":"/cn/1153/1/4","title":"古洞"},{"slug":"/cn/1153/1/5","title":"客次逢乡人"},{"slug":"/cn/1153/1/6","title":"旅怀"},{"slug":"/cn/1153/1/7","title":"送李伯开"},{"slug":"/cn/1153/1/8","title":"客子"},{"slug":"/cn/1153/1/9","title":"送某护军解官归罗浮奉母塞上送友人归养"},{"slug":"/cn/1153/1/10","title":"柬伯起"},{"slug":"/cn/1153/1/11","title":"梁明府席上咏锦竹"},{"slug":"/cn/1153/1/12","title":"送罗澄白"},{"slug":"/cn/1153/1/13","title":"溪上"},{"slug":"/cn/1153/1/14","title":"还山","child":[{"slug":"/cn/1153/1/14/1","title":"其一"},{"slug":"/cn/1153/1/14/2","title":"其二"}]},{"slug":"/cn/1153/1/15","title":"春江泛舟同韩孟郁赋"},{"slug":"/cn/1153/1/16","title":"雨后泊桃花溪"},{"slug":"/cn/1153/1/17","title":"赠某小史"},{"slug":"/cn/1153/1/18","title":"古意"},{"slug":"/cn/1153/1/19","title":"闺怨"},{"slug":"/cn/1153/1/20","title":"怀张约之"},{"slug":"/cn/1153/1/21","title":"度小湘"},{"slug":"/cn/1153/1/22","title":"寻梅"},{"slug":"/cn/1153/1/23","title":"归至澜石留别梁璘叔"},{"slug":"/cn/1153/1/24","title":"同马伯超黎君献彭伯时访罗集虚溪上分得七阳韵"},{"slug":"/cn/1153/1/25","title":"泊峡口"},{"slug":"/cn/1153/1/26","title":"入峡"},{"slug":"/cn/1153/1/27","title":"咏水中新月"},{"slug":"/cn/1153/1/28","title":"春风"},{"slug":"/cn/1153/1/29","title":"游星岩"},{"slug":"/cn/1153/1/30","title":"紫竹洞"},{"slug":"/cn/1153/1/31","title":"玉虚宫"},{"slug":"/cn/1153/1/32","title":"访友不值（一作释通岸诗）"},{"slug":"/cn/1153/1/33","title":"山中寄怀杜远侯诸子"},{"slug":"/cn/1153/1/34","title":"访朱季美环谷庄居"},{"slug":"/cn/1153/1/35","title":"题罗右良泊如斋"},{"slug":"/cn/1153/1/36","title":"晚渡增江（一作释通岸诗）"},{"slug":"/cn/1153/1/37","title":"寄答梁明叔"},{"slug":"/cn/1153/1/38","title":"怀马伯起"},{"slug":"/cn/1153/1/39","title":"怀罗集虚"},{"slug":"/cn/1153/1/40","title":"发油田"},{"slug":"/cn/1153/1/41","title":"溪竹"},{"slug":"/cn/1153/1/42","title":"湖上作"},{"slug":"/cn/1153/1/43","title":"赠伯燮陈子"},{"slug":"/cn/1153/1/44","title":"过黄逢一"},{"slug":"/cn/1153/1/45","title":"赠良公"},{"slug":"/cn/1153/1/46","title":"水西别业新成"},{"slug":"/cn/1153/1/47","title":"园居"},{"slug":"/cn/1153/1/48","title":"早春偕唐美卿游桃花坞"},{"slug":"/cn/1153/1/49","title":"书怀"},{"slug":"/cn/1153/1/50","title":"送客游秣陵"},{"slug":"/cn/1153/1/51","title":"柬罗集虚"},{"slug":"/cn/1153/1/52","title":"怀王元卿"},{"slug":"/cn/1153/1/53","title":"柬黎孺旬"},{"slug":"/cn/1153/1/54","title":"怀仙诗寄唐美卿于三山"},{"slug":"/cn/1153/1/55","title":"僧林"},{"slug":"/cn/1153/1/56","title":"送梁无畸"},{"slug":"/cn/1153/1/57","title":"答黎美璋"},{"slug":"/cn/1153/1/58","title":"同黄元卿张约之梁日良游月溪留宿"},{"slug":"/cn/1153/1/59","title":"怀朱季美"},{"slug":"/cn/1153/1/60","title":"归雁"},{"slug":"/cn/1153/1/61","title":"村居","child":[{"slug":"/cn/1153/1/61/1","title":"其一"},{"slug":"/cn/1153/1/61/2","title":"其二"},{"slug":"/cn/1153/1/61/3","title":"其三"}]},{"slug":"/cn/1153/1/62","title":"解嘲","child":[{"slug":"/cn/1153/1/62/1","title":"其一"},{"slug":"/cn/1153/1/62/2","title":"其二"}]},{"slug":"/cn/1153/1/63","title":"赠袁尔昌"},{"slug":"/cn/1153/1/64","title":"波罗庙"},{"slug":"/cn/1153/1/65","title":"北山绝顶"},{"slug":"/cn/1153/1/66","title":"赠汪伯耳","child":[{"slug":"/cn/1153/1/66/1","title":"其一"},{"slug":"/cn/1153/1/66/2","title":"其二"}]},{"slug":"/cn/1153/1/67","title":"暮雨"},{"slug":"/cn/1153/1/68","title":"江亭晓望怀幼良罗子"},{"slug":"/cn/1153/1/69","title":"过王元卿山居"},{"slug":"/cn/1153/1/70","title":"上巳东山社集"},{"slug":"/cn/1153/1/71","title":"茅堂"},{"slug":"/cn/1153/1/72","title":"独坐"},{"slug":"/cn/1153/1/73","title":"雨过"},{"slug":"/cn/1153/1/74","title":"紫竹洞"},{"slug":"/cn/1153/1/75","title":"晚晴"},{"slug":"/cn/1153/1/76","title":"送黄元卿"},{"slug":"/cn/1153/1/77","title":"送李嗣良"},{"slug":"/cn/1153/1/78","title":"寄陈来献"},{"slug":"/cn/1153/1/79","title":"怀罗季作"},{"slug":"/cn/1153/1/80","title":"舟过安远喜钟彦辅徐慈明李伯脩出送"},{"slug":"/cn/1153/1/81","title":"怀刘思约"},{"slug":"/cn/1153/1/82","title":"入关留别袁大司马"},{"slug":"/cn/1153/1/83","title":"留别梁非馨"},{"slug":"/cn/1153/1/84","title":"湖上同邝公路家定夫作"},{"slug":"/cn/1153/1/85","title":"送安仲"},{"slug":"/cn/1153/1/86","title":"寿韩寅仲"},{"slug":"/cn/1153/1/87","title":"送吴子远次韵"},{"slug":"/cn/1153/1/88","title":"同阮集之泛舟游三山遇杜退思上公车过访"},{"slug":"/cn/1153/1/89","title":"午日阮集之招同计无不璩山甫叶开美潘次鲁徐介白林六长方圣羽徐介夫集警园次韵"},{"slug":"/cn/1153/1/90","title":"赋得高杨拂地垂"},{"slug":"/cn/1153/1/91","title":"漓江"},{"slug":"/cn/1153/1/92","title":"南野"},{"slug":"/cn/1153/1/93","title":"罗季作饯别"},{"slug":"/cn/1153/1/94","title":"题徐氏园"},{"slug":"/cn/1153/1/95","title":"送黎孺旬之官闽中"},{"slug":"/cn/1153/1/96","title":"闰八月十四夕待月钟氏映日池馆遇雨"},{"slug":"/cn/1153/1/97","title":"访袁道生新居"},{"slug":"/cn/1153/1/98","title":"酬王子翼先"},{"slug":"/cn/1153/1/99","title":"端阳赠陈伯燮新婚"},{"slug":"/cn/1153/1/100","title":"咏朋泉","child":[{"slug":"/cn/1153/1/100/1","title":"其一"},{"slug":"/cn/1153/1/100/2","title":"其二"}]},{"slug":"/cn/1153/1/101","title":"严子陵祠"},{"slug":"/cn/1153/1/102","title":"泛舟桃花溪同刘萧郎"},{"slug":"/cn/1153/1/103","title":"送汪子"},{"slug":"/cn/1153/1/104","title":"不是庵"},{"slug":"/cn/1153/1/105","title":"录别","child":[{"slug":"/cn/1153/1/105/1","title":"其一"},{"slug":"/cn/1153/1/105/2","title":"其二"}]},{"slug":"/cn/1153/1/106","title":"哭周昆彦","child":[{"slug":"/cn/1153/1/106/1","title":"其一"},{"slug":"/cn/1153/1/106/2","title":"其二"}]},{"slug":"/cn/1153/1/107","title":"徐孟孺招游新筑还集景文堂","child":[{"slug":"/cn/1153/1/107/1","title":"其一"},{"slug":"/cn/1153/1/107/2","title":"其二"}]},{"slug":"/cn/1153/1/108","title":"梅花和邝湛若"},{"slug":"/cn/1153/1/109","title":"寄袁道生","child":[{"slug":"/cn/1153/1/109/1","title":"其一"},{"slug":"/cn/1153/1/109/2","title":"其二"}]},{"slug":"/cn/1153/1/110","title":"答陈彦升兼以为别"},{"slug":"/cn/1153/1/111","title":"哭袁大玉符卿","child":[{"slug":"/cn/1153/1/111/1","title":"其一"},{"slug":"/cn/1153/1/111/2","title":"其二"},{"slug":"/cn/1153/1/111/3","title":"其三"},{"slug":"/cn/1153/1/111/4","title":"其四"},{"slug":"/cn/1153/1/111/5","title":"其五"}]},{"slug":"/cn/1153/1/112","title":"答刘茂生寄怀"},{"slug":"/cn/1153/1/113","title":"梅花六咏","child":[{"slug":"/cn/1153/1/113/1","title":"其一"},{"slug":"/cn/1153/1/113/2","title":"其二"},{"slug":"/cn/1153/1/113/3","title":"其三"},{"slug":"/cn/1153/1/113/4","title":"其四"},{"slug":"/cn/1153/1/113/5","title":"其五"},{"slug":"/cn/1153/1/113/6","title":"其六"}]},{"slug":"/cn/1153/1/114","title":"青楼曲","child":[{"slug":"/cn/1153/1/114/1","title":"其一"},{"slug":"/cn/1153/1/114/2","title":"其二"},{"slug":"/cn/1153/1/114/3","title":"其三"}]},{"slug":"/cn/1153/1/115","title":"游湛抡卿水亭"},{"slug":"/cn/1153/1/116","title":"道中寄张孟奇太守"},{"slug":"/cn/1153/1/117","title":"见日庵忆谭永明山人"},{"slug":"/cn/1153/1/118","title":"玉女峰"},{"slug":"/cn/1153/1/119","title":"罗浮道中四首","child":[{"slug":"/cn/1153/1/119/1","title":"其一"},{"slug":"/cn/1153/1/119/2","title":"其二"},{"slug":"/cn/1153/1/119/3","title":"其三"},{"slug":"/cn/1153/1/119/4","title":"其四"}]},{"slug":"/cn/1153/1/120","title":"梅花村"},{"slug":"/cn/1153/1/121","title":"彩云轩"},{"slug":"/cn/1153/1/122","title":"端溪"},{"slug":"/cn/1153/1/123","title":"发韶州"},{"slug":"/cn/1153/1/124","title":"浮丘山居十首","child":[{"slug":"/cn/1153/1/124/1","title":"其一"},{"slug":"/cn/1153/1/124/2","title":"其二"},{"slug":"/cn/1153/1/124/3","title":"其三"},{"slug":"/cn/1153/1/124/4","title":"其四"},{"slug":"/cn/1153/1/124/5","title":"其五"},{"slug":"/cn/1153/1/124/6","title":"其六"},{"slug":"/cn/1153/1/124/7","title":"其七"},{"slug":"/cn/1153/1/124/8","title":"其八"},{"slug":"/cn/1153/1/124/9","title":"其九"},{"slug":"/cn/1153/1/124/10","title":"其十"}]},{"slug":"/cn/1153/1/125","title":"佳人年十五为潘乾父赋","child":[{"slug":"/cn/1153/1/125/1","title":"其一"},{"slug":"/cn/1153/1/125/2","title":"其二"}]},{"slug":"/cn/1153/1/126","title":"浮丘社集同张孟奇黎是因欧嘉可黄逢永张子台分得鱼字"},{"slug":"/cn/1153/1/127","title":"送陈来献游武夷"},{"slug":"/cn/1153/1/128","title":"寿王侍御"},{"slug":"/cn/1153/1/129","title":"人日喜晴"},{"slug":"/cn/1153/1/130","title":"并蒂兰为梁幼宁先生赋"},{"slug":"/cn/1153/1/131","title":"赠李赞夫"},{"slug":"/cn/1153/1/132","title":"鸡洲阻雨同卢一清韩孟郁赋"},{"slug":"/cn/1153/1/133","title":"访冯稚谟文赏斋次一清韵"},{"slug":"/cn/1153/1/134","title":"寿潘母"},{"slug":"/cn/1153/1/135","title":"韩孟郁招同黄宫谕刘宪副高太守梁韩二明府暨苏梁诸公集浮丘步寅仲韵","child":[{"slug":"/cn/1153/1/135/1","title":"其一"},{"slug":"/cn/1153/1/135/2","title":"其二"},{"slug":"/cn/1153/1/135/3","title":"其三"},{"slug":"/cn/1153/1/135/4","title":"其四"},{"slug":"/cn/1153/1/135/5","title":"其五"}]},{"slug":"/cn/1153/1/136","title":"送盛德生","child":[{"slug":"/cn/1153/1/136/1","title":"其一"},{"slug":"/cn/1153/1/136/2","title":"其二"}]},{"slug":"/cn/1153/1/137","title":"送卢一清西游"},{"slug":"/cn/1153/1/138","title":"送李果卿之官楚中"},{"slug":"/cn/1153/1/139","title":"送潘乾父游罗浮"},{"slug":"/cn/1153/1/140","title":"咏梁幼宁先生庭前菖蒲花"},{"slug":"/cn/1153/1/141","title":"送龙门令内召"},{"slug":"/cn/1153/1/142","title":"镜园和邓玄度步韵","child":[{"slug":"/cn/1153/1/142/1","title":"其一"},{"slug":"/cn/1153/1/142/2","title":"其二"},{"slug":"/cn/1153/1/142/3","title":"其三"},{"slug":"/cn/1153/1/142/4","title":"其四"},{"slug":"/cn/1153/1/142/5","title":"其五"},{"slug":"/cn/1153/1/142/6","title":"其六"},{"slug":"/cn/1153/1/142/7","title":"其七"},{"slug":"/cn/1153/1/142/8","title":"其八"},{"slug":"/cn/1153/1/142/9","title":"其九"},{"slug":"/cn/1153/1/142/10","title":"其十"},{"slug":"/cn/1153/1/142/11","title":"其十一"},{"slug":"/cn/1153/1/142/12","title":"其十二"},{"slug":"/cn/1153/1/142/13","title":"其十三"},{"slug":"/cn/1153/1/142/14","title":"其十四"},{"slug":"/cn/1153/1/142/15","title":"其十五"}]},{"slug":"/cn/1153/1/143","title":"送李木仙","child":[{"slug":"/cn/1153/1/143/1","title":"其一"},{"slug":"/cn/1153/1/143/2","title":"其二"}]},{"slug":"/cn/1153/1/144","title":"送孙稚明","child":[{"slug":"/cn/1153/1/144/1","title":"其一"},{"slug":"/cn/1153/1/144/2","title":"其二"},{"slug":"/cn/1153/1/144/3","title":"其三"}]},{"slug":"/cn/1153/1/145","title":"雨后阮集之招同林六长徐介白程荩臣集咏怀堂分得八庚","child":[{"slug":"/cn/1153/1/145/1","title":"其一"},{"slug":"/cn/1153/1/145/2","title":"其二"}]},{"slug":"/cn/1153/1/146","title":"沥湖渔棹为张道尊赋","child":[{"slug":"/cn/1153/1/146/1","title":"其一"},{"slug":"/cn/1153/1/146/2","title":"其二"}]},{"slug":"/cn/1153/1/147","title":"吴充符招同集之游修竹庵","child":[{"slug":"/cn/1153/1/147/1","title":"其一"},{"slug":"/cn/1153/1/147/2","title":"其二"}]},{"slug":"/cn/1153/1/148","title":"送黎君选之官兴业","child":[{"slug":"/cn/1153/1/148/1","title":"其一"},{"slug":"/cn/1153/1/148/2","title":"其二"}]},{"slug":"/cn/1153/1/149","title":"过姑熟访曹元甫光禄","child":[{"slug":"/cn/1153/1/149/1","title":"其一"},{"slug":"/cn/1153/1/149/2","title":"其二"}]},{"slug":"/cn/1153/1/150","title":"阮宝夫将游朗宁过访啸楼止宿有赠次其韵","child":[{"slug":"/cn/1153/1/150/1","title":"其一"},{"slug":"/cn/1153/1/150/2","title":"其二"}]},{"slug":"/cn/1153/1/151","title":"送李美发","child":[{"slug":"/cn/1153/1/151/1","title":"其一"},{"slug":"/cn/1153/1/151/2","title":"其二"}]},{"slug":"/cn/1153/1/152","title":"塞上答沈璧父"},{"slug":"/cn/1153/1/153","title":"斐园席上咏物限韵二首","child":[{"slug":"/cn/1153/1/153/1","title":"其一 古宣炉"},{"slug":"/cn/1153/1/153/2","title":"其二 古松雪砚"}]},{"slug":"/cn/1153/1/154","title":"寿潮阳莫郡丞"},{"slug":"/cn/1153/1/155","title":"和李宫詹过桃源有感示家明府鸣周次韵"},{"slug":"/cn/1153/1/156","title":"以桃杯及西帨寿李伯襄各系以诗","child":[{"slug":"/cn/1153/1/156/1","title":"其一"},{"slug":"/cn/1153/1/156/2","title":"其二"}]},{"slug":"/cn/1153/1/157","title":"泊园为杨元孺都督赋","child":[{"slug":"/cn/1153/1/157/1","title":"其一"},{"slug":"/cn/1153/1/157/2","title":"其二"},{"slug":"/cn/1153/1/157/3","title":"其三"}]},{"slug":"/cn/1153/1/158","title":"咏素馨花灯"},{"slug":"/cn/1153/1/159","title":"夕阳"},{"slug":"/cn/1153/1/160","title":"送无公"},{"slug":"/cn/1153/1/161","title":"林叔宝将归莆中时余方东游作此为别"},{"slug":"/cn/1153/1/162","title":"送吴济之游吴"},{"slug":"/cn/1153/1/163","title":"题朱惟四小青林"},{"slug":"/cn/1153/1/164","title":"游朱惟乐瑶林园还因过惟卓北郭草堂"},{"slug":"/cn/1153/1/165","title":"咏钓竿"},{"slug":"/cn/1153/1/166","title":"南园"},{"slug":"/cn/1153/1/167","title":"过黄居士山居","child":[{"slug":"/cn/1153/1/167/1","title":"其一"},{"slug":"/cn/1153/1/167/2","title":"其二"}]},{"slug":"/cn/1153/1/168","title":"送刘冲倩拥妾游罗浮"},{"slug":"/cn/1153/1/169","title":"题梁元珍修远居"},{"slug":"/cn/1153/1/170","title":"送徐山人"},{"slug":"/cn/1153/1/171","title":"送刘广文宰祁阳"},{"slug":"/cn/1153/1/172","title":"送刘郡丞之任庆阳"},{"slug":"/cn/1153/1/173","title":"送张提盐入觐"},{"slug":"/cn/1153/1/174","title":"和邓玄度少参归兴十首","child":[{"slug":"/cn/1153/1/174/1","title":"其一"},{"slug":"/cn/1153/1/174/2","title":"其二"},{"slug":"/cn/1153/1/174/3","title":"其三"},{"slug":"/cn/1153/1/174/4","title":"其四"},{"slug":"/cn/1153/1/174/5","title":"其五"},{"slug":"/cn/1153/1/174/6","title":"其六"},{"slug":"/cn/1153/1/174/7","title":"其七"},{"slug":"/cn/1153/1/174/8","title":"其八"},{"slug":"/cn/1153/1/174/9","title":"其九"},{"slug":"/cn/1153/1/174/10","title":"其十"}]},{"slug":"/cn/1153/1/175","title":"学博陈冲师奏最"},{"slug":"/cn/1153/1/176","title":"答韩寅仲诗扇见寄"},{"slug":"/cn/1153/1/177","title":"答袁朗生"},{"slug":"/cn/1153/1/178","title":"寿东官周令公"},{"slug":"/cn/1153/1/179","title":"秋夜"},{"slug":"/cn/1153/1/180","title":"怀陈子"},{"slug":"/cn/1153/1/181","title":"感秋柬黎马龙诸子"},{"slug":"/cn/1153/1/182","title":"春水"},{"slug":"/cn/1153/1/183","title":"春郊"}]},{"slug":"/cn/1153/2","title":"七言律诗","child":[{"slug":"/cn/1153/2/1","title":"赠王羽卿大将军"},{"slug":"/cn/1153/2/2","title":"冬日黎氏北园社集"},{"slug":"/cn/1153/2/3","title":"行经罗浮"},{"slug":"/cn/1153/2/4","title":"客中寄梁伯遐"},{"slug":"/cn/1153/2/5","title":"送潘子上兼寄其伯氏"},{"slug":"/cn/1153/2/6","title":"送汪伯耳"},{"slug":"/cn/1153/2/7","title":"灵芝为魏少参赋"},{"slug":"/cn/1153/2/8","title":"送王大将军"},{"slug":"/cn/1153/2/9","title":"元夕赋得䌽花树"},{"slug":"/cn/1153/2/10","title":"李伯襄太史招同马伯起赵裕子载酒访余丹丘各赋二律","child":[{"slug":"/cn/1153/2/10/1","title":"其一"},{"slug":"/cn/1153/2/10/2","title":"其二"}]},{"slug":"/cn/1153/2/11","title":"送张垣孺"},{"slug":"/cn/1153/2/12","title":"赠潘子明"},{"slug":"/cn/1153/2/13","title":"花影"},{"slug":"/cn/1153/2/14","title":"无题为刘师浩作"},{"slug":"/cn/1153/2/15","title":"送方士昭还漳州"},{"slug":"/cn/1153/2/16","title":"韩宾仲专壑山房分得春字"},{"slug":"/cn/1153/2/17","title":"宿冲虚观"},{"slug":"/cn/1153/2/18","title":"罗浮山中四首","child":[{"slug":"/cn/1153/2/18/1","title":"其一"},{"slug":"/cn/1153/2/18/2","title":"其二"},{"slug":"/cn/1153/2/18/3","title":"其三"},{"slug":"/cn/1153/2/18/4","title":"其四"}]},{"slug":"/cn/1153/2/19","title":"登瑶石台怀黎惟敬先生兼赠君献"},{"slug":"/cn/1153/2/20","title":"寄李伯起李伯襄诸子"},{"slug":"/cn/1153/2/21","title":"寓袁仲符署中黄与东来访"},{"slug":"/cn/1153/2/22","title":"袁司李约同游湘山不果赴"},{"slug":"/cn/1153/2/23","title":"归舟作"},{"slug":"/cn/1153/2/24","title":"酌酒与客效唐伯虎"},{"slug":"/cn/1153/2/25","title":"访邓玄度先生于濠上客舍别后以诗见寄次韵"},{"slug":"/cn/1153/2/26","title":"为玄度寿母","child":[{"slug":"/cn/1153/2/26/1","title":"其一"},{"slug":"/cn/1153/2/26/2","title":"其二"}]},{"slug":"/cn/1153/2/27","title":"寄答欧子建"},{"slug":"/cn/1153/2/28","title":"梁幼宁明府招赏红梅"},{"slug":"/cn/1153/2/29","title":"和邓玄度少参楼居诗次韵","child":[{"slug":"/cn/1153/2/29/1","title":"其一"},{"slug":"/cn/1153/2/29/2","title":"其二"},{"slug":"/cn/1153/2/29/3","title":"其三"},{"slug":"/cn/1153/2/29/4","title":"其四"}]},{"slug":"/cn/1153/2/30","title":"梁幼宁明府同杜远侯过集浮丘分得梁字"},{"slug":"/cn/1153/2/31","title":"送兵宪罗公入觐","child":[{"slug":"/cn/1153/2/31/1","title":"其一"},{"slug":"/cn/1153/2/31/2","title":"其二"}]},{"slug":"/cn/1153/2/32","title":"入西樵同李伯襄戴公纶彭伯时伍国开有作"},{"slug":"/cn/1153/2/33","title":"西樵晓发"},{"slug":"/cn/1153/2/34","title":"出西樵留别李太史"},{"slug":"/cn/1153/2/35","title":"花朝"},{"slug":"/cn/1153/2/36","title":"赠阳春钱明府"},{"slug":"/cn/1153/2/37","title":"同韩孟郁卢一清访李太史宿建霞楼"},{"slug":"/cn/1153/2/38","title":"访李太史因赠"},{"slug":"/cn/1153/2/39","title":"题孟郁朵云山房"},{"slug":"/cn/1153/2/40","title":"送傅贞父"},{"slug":"/cn/1153/2/41","title":"赠苍梧陈太守"},{"slug":"/cn/1153/2/42","title":"罗浮山下别韩绪仲太史"},{"slug":"/cn/1153/2/43","title":"邓玄度招同张孟奇韩孟郁诸公游旗峰"},{"slug":"/cn/1153/2/44","title":"寄李伯襄编修"},{"slug":"/cn/1153/2/45","title":"送麦子中之官荔浦"},{"slug":"/cn/1153/2/46","title":"梁幼宁先生过访南渚留赠用韵赋答"},{"slug":"/cn/1153/2/47","title":"送何大将军"},{"slug":"/cn/1153/2/48","title":"岁寒桃实为叶盛温赋"},{"slug":"/cn/1153/2/49","title":"次韵答汪士元参军时士元方奉檄备舟江北以济援辽之师"},{"slug":"/cn/1153/2/50","title":"送袁元约出关兼寄袁自如监军"},{"slug":"/cn/1153/2/51","title":"秋夕王潜父李参寰见过"},{"slug":"/cn/1153/2/52","title":"冈州遇侄仲良因赠"},{"slug":"/cn/1153/2/53","title":"燕郎酬李无核","child":[{"slug":"/cn/1153/2/53/1","title":"其一"},{"slug":"/cn/1153/2/53/2","title":"其二"}]},{"slug":"/cn/1153/2/54","title":"闻警答李无核"},{"slug":"/cn/1153/2/55","title":"陈抑之宪副招集东皋"},{"slug":"/cn/1153/2/56","title":"何龙友太史招游西樵不果诗以寄之","child":[{"slug":"/cn/1153/2/56/1","title":"其一"},{"slug":"/cn/1153/2/56/2","title":"其二"}]},{"slug":"/cn/1153/2/57","title":"漓江军中柬袁仲符兵部"},{"slug":"/cn/1153/2/58","title":"午日泗上过韩宗伯出掌南院招饮舟中同李宫詹赵裕子"},{"slug":"/cn/1153/2/59","title":"过邓太素刺史沁园留酌分得花字"},{"slug":"/cn/1153/2/60","title":"野泊"},{"slug":"/cn/1153/2/61","title":"黎有道拥丽人入幕筑别院居之戏赠"},{"slug":"/cn/1153/2/62","title":"曲中","child":[{"slug":"/cn/1153/2/62/1","title":"其一"},{"slug":"/cn/1153/2/62/2","title":"其二"}]},{"slug":"/cn/1153/2/63","title":"同董弱红夜泊静慈寺有怀马明府"},{"slug":"/cn/1153/2/64","title":"社中诸子再饯别限韵"},{"slug":"/cn/1153/2/65","title":"楼居答黎美周"},{"slug":"/cn/1153/2/66","title":"斐园观梅有赠"},{"slug":"/cn/1153/2/67","title":"七夕何文玉招同诸子载妓清泛时文玉新得佳人"},{"slug":"/cn/1153/2/68","title":"送熊振予西还兼寄萧广生"},{"slug":"/cn/1153/2/69","title":"无题戏拟王君奉（君奉所欢名青青）"},{"slug":"/cn/1153/2/70","title":"梅关道中①","child":[{"slug":"/cn/1153/2/70/1","title":"其一"},{"slug":"/cn/1153/2/70/2","title":"其二"}]},{"slug":"/cn/1153/2/71","title":"花朝过蕉溪"},{"slug":"/cn/1153/2/72","title":"丁卯感秋"},{"slug":"/cn/1153/2/73","title":"丁卯九日集何太史斋中（时大行皇帝初升遐）"},{"slug":"/cn/1153/2/74","title":"出关次横浦","child":[{"slug":"/cn/1153/2/74/1","title":"其一"},{"slug":"/cn/1153/2/74/2","title":"其二"}]},{"slug":"/cn/1153/2/75","title":"金陵春日"},{"slug":"/cn/1153/2/76","title":"酬何龙友太史"},{"slug":"/cn/1153/2/77","title":"寓虎丘李如谷观察过访"},{"slug":"/cn/1153/2/78","title":"塞下曲（锦州秋日作）"},{"slug":"/cn/1153/2/79","title":"送郭圣襄大行使楚"},{"slug":"/cn/1153/2/80","title":"归至南昌罗季作郡丞出访"},{"slug":"/cn/1153/2/81","title":"送叶少府参楚黄军事暂还粤中"},{"slug":"/cn/1153/2/82","title":"送温觉斯游金陵"},{"slug":"/cn/1153/2/83","title":"寄张太史"},{"slug":"/cn/1153/2/84","title":"游燕矶同李公詹"},{"slug":"/cn/1153/2/85","title":"九日集李公詹别署（公有长歌送予出塞）"},{"slug":"/cn/1153/2/86","title":"闻今上驻跸端州恭纪","child":[{"slug":"/cn/1153/2/86/1","title":"其一 原作"},{"slug":"/cn/1153/2/86/2","title":"其二 改一"},{"slug":"/cn/1153/2/86/3","title":"其三 改二"}]},{"slug":"/cn/1153/2/87","title":"弘光恭纪"},{"slug":"/cn/1153/2/88","title":"初春偕诸子游峒山"},{"slug":"/cn/1153/2/89","title":"往行在赋赠","child":[{"slug":"/cn/1153/2/89/1","title":"其一"},{"slug":"/cn/1153/2/89/2","title":"其二"}]},{"slug":"/cn/1153/2/90","title":"乙酉元夕辞弋何赏灯步韵"},{"slug":"/cn/1153/2/91","title":"和弋何更名作"},{"slug":"/cn/1153/2/92","title":"苏元易贻湛用喈彩树牡丹招赏因赋"},{"slug":"/cn/1153/2/93","title":"寿瑶台翁八十一"},{"slug":"/cn/1153/2/94","title":"峡寺"}]},{"slug":"/cn/1153/3","title":"五言绝句","child":[{"slug":"/cn/1153/3/1","title":"水西寓目同梁幼宁明府赋","child":[{"slug":"/cn/1153/3/1/1","title":"其一"},{"slug":"/cn/1153/3/1/2","title":"其二"},{"slug":"/cn/1153/3/1/3","title":"其三"},{"slug":"/cn/1153/3/1/4","title":"其四"}]},{"slug":"/cn/1153/3/2","title":"山居","child":[{"slug":"/cn/1153/3/2/1","title":"其一"},{"slug":"/cn/1153/3/2/2","title":"其二"}]},{"slug":"/cn/1153/3/3","title":"梁明府茅冈杂咏","child":[{"slug":"/cn/1153/3/3/1","title":"其一 香茅宇"},{"slug":"/cn/1153/3/3/2","title":"其二 列岫亭"},{"slug":"/cn/1153/3/3/3","title":"其三 桔槔庑"},{"slug":"/cn/1153/3/3/4","title":"其四 华平沼"},{"slug":"/cn/1153/3/3/5","title":"其五 采菱渡"},{"slug":"/cn/1153/3/3/6","title":"其六 扶荔湾"},{"slug":"/cn/1153/3/3/7","title":"其七 红梅径"},{"slug":"/cn/1153/3/3/8","title":"其八 蟀蟋坪"}]},{"slug":"/cn/1153/3/4","title":"菰渚"},{"slug":"/cn/1153/3/5","title":"蕉林"},{"slug":"/cn/1153/3/6","title":"山居杂咏","child":[{"slug":"/cn/1153/3/6/1","title":"其一"},{"slug":"/cn/1153/3/6/2","title":"其二"}]},{"slug":"/cn/1153/3/7","title":"七夕有怀"},{"slug":"/cn/1153/3/8","title":"怀人"},{"slug":"/cn/1153/3/9","title":"送客"},{"slug":"/cn/1153/3/10","title":"题柿送刘少参入贺"},{"slug":"/cn/1153/3/11","title":"桃源洞"},{"slug":"/cn/1153/3/12","title":"见日庵"},{"slug":"/cn/1153/3/13","title":"锦云岩"},{"slug":"/cn/1153/3/14","title":"麻姑峰"},{"slug":"/cn/1153/3/15","title":"白云洞"},{"slug":"/cn/1153/3/16","title":"分绿桥"},{"slug":"/cn/1153/3/17","title":"听莺步"},{"slug":"/cn/1153/3/18","title":"斐园杂咏十一首","child":[{"slug":"/cn/1153/3/18/1","title":"其一 恬远楼"},{"slug":"/cn/1153/3/18/2","title":"其二 桐君阁"},{"slug":"/cn/1153/3/18/3","title":"其三 北望台"},{"slug":"/cn/1153/3/18/4","title":"其四 写叶山房"},{"slug":"/cn/1153/3/18/5","title":"其五 问景台"},{"slug":"/cn/1153/3/18/6","title":"其六 青鸟轩"},{"slug":"/cn/1153/3/18/7","title":"其七 曲引"},{"slug":"/cn/1153/3/18/8","title":"其八 馀轩"},{"slug":"/cn/1153/3/18/9","title":"其九 云门"},{"slug":"/cn/1153/3/18/10","title":"其十 琅玕沜"},{"slug":"/cn/1153/3/18/11","title":"其十一 清浣"}]}]},{"slug":"/cn/1153/4","title":"七言绝句","child":[{"slug":"/cn/1153/4/1","title":"少年行","child":[{"slug":"/cn/1153/4/1/1","title":"其一"},{"slug":"/cn/1153/4/1/2","title":"其二"}]},{"slug":"/cn/1153/4/2","title":"明妃曲"},{"slug":"/cn/1153/4/3","title":"送客游广陵"},{"slug":"/cn/1153/4/4","title":"送客还楚"},{"slug":"/cn/1153/4/5","title":"送客西游"},{"slug":"/cn/1153/4/6","title":"清溪"},{"slug":"/cn/1153/4/7","title":"都督王公阅兵海上歌","child":[{"slug":"/cn/1153/4/7/1","title":"其一"},{"slug":"/cn/1153/4/7/2","title":"其二"},{"slug":"/cn/1153/4/7/3","title":"其三"},{"slug":"/cn/1153/4/7/4","title":"其四"},{"slug":"/cn/1153/4/7/5","title":"其五"},{"slug":"/cn/1153/4/7/6","title":"其六"},{"slug":"/cn/1153/4/7/7","title":"其七"},{"slug":"/cn/1153/4/7/8","title":"其八"}]},{"slug":"/cn/1153/4/8","title":"游仙曲","child":[{"slug":"/cn/1153/4/8/1","title":"其一"},{"slug":"/cn/1153/4/8/2","title":"其二"}]},{"slug":"/cn/1153/4/9","title":"怀仙引和黎君献","child":[{"slug":"/cn/1153/4/9/1","title":"其一"},{"slug":"/cn/1153/4/9/2","title":"其二"},{"slug":"/cn/1153/4/9/3","title":"其三"},{"slug":"/cn/1153/4/9/4","title":"其四"}]},{"slug":"/cn/1153/4/10","title":"元夕曲","child":[{"slug":"/cn/1153/4/10/1","title":"其一"},{"slug":"/cn/1153/4/10/2","title":"其二"},{"slug":"/cn/1153/4/10/3","title":"其三"}]},{"slug":"/cn/1153/4/11","title":"哭崔季嘿","child":[{"slug":"/cn/1153/4/11/1","title":"其一"},{"slug":"/cn/1153/4/11/2","title":"其二"},{"slug":"/cn/1153/4/11/3","title":"其三"},{"slug":"/cn/1153/4/11/4","title":"其四"},{"slug":"/cn/1153/4/11/5","title":"其五"},{"slug":"/cn/1153/4/11/6","title":"其六"},{"slug":"/cn/1153/4/11/7","title":"其七"},{"slug":"/cn/1153/4/11/8","title":"其八"}]},{"slug":"/cn/1153/4/12","title":"闻征黎官军奏捷寄王都督","child":[{"slug":"/cn/1153/4/12/1","title":"其一"},{"slug":"/cn/1153/4/12/2","title":"其二"},{"slug":"/cn/1153/4/12/3","title":"其三"}]},{"slug":"/cn/1153/4/13","title":"寿萧少宰","child":[{"slug":"/cn/1153/4/13/1","title":"其一"},{"slug":"/cn/1153/4/13/2","title":"其二"},{"slug":"/cn/1153/4/13/3","title":"其三"}]},{"slug":"/cn/1153/4/14","title":"题玉兰送刘少参入贺"},{"slug":"/cn/1153/4/15","title":"咏牡丹"},{"slug":"/cn/1153/4/16","title":"听乙姬弹琴"},{"slug":"/cn/1153/4/17","title":"黄逢一席上戏赠诸侍子二首","child":[{"slug":"/cn/1153/4/17/1","title":"其一"},{"slug":"/cn/1153/4/17/2","title":"其二"}]},{"slug":"/cn/1153/4/18","title":"月夜闻啸"},{"slug":"/cn/1153/4/19","title":"杂记八首","child":[{"slug":"/cn/1153/4/19/1","title":"其一"},{"slug":"/cn/1153/4/19/2","title":"其二"},{"slug":"/cn/1153/4/19/3","title":"其三"},{"slug":"/cn/1153/4/19/4","title":"其四"},{"slug":"/cn/1153/4/19/5","title":"其五"},{"slug":"/cn/1153/4/19/6","title":"其六"},{"slug":"/cn/1153/4/19/7","title":"其七"},{"slug":"/cn/1153/4/19/8","title":"其八"}]},{"slug":"/cn/1153/4/20","title":"戏为木客解嘲"},{"slug":"/cn/1153/4/21","title":"戏和梁幼宁明府城西步月即事之作","child":[{"slug":"/cn/1153/4/21/1","title":"其一"},{"slug":"/cn/1153/4/21/2","title":"其二"}]},{"slug":"/cn/1153/4/22","title":"广州元夜歌","child":[{"slug":"/cn/1153/4/22/1","title":"其一"},{"slug":"/cn/1153/4/22/2","title":"其二"},{"slug":"/cn/1153/4/22/3","title":"其三"},{"slug":"/cn/1153/4/22/4","title":"其四"},{"slug":"/cn/1153/4/22/5","title":"其五"},{"slug":"/cn/1153/4/22/6","title":"其六"},{"slug":"/cn/1153/4/22/7","title":"其七"},{"slug":"/cn/1153/4/22/8","title":"其八"},{"slug":"/cn/1153/4/22/9","title":"其九"},{"slug":"/cn/1153/4/22/10","title":"其十"}]},{"slug":"/cn/1153/4/23","title":"为伯修挥使寿母"},{"slug":"/cn/1153/4/24","title":"无题和韩孟郁","child":[{"slug":"/cn/1153/4/24/1","title":"其一"},{"slug":"/cn/1153/4/24/2","title":"其二"},{"slug":"/cn/1153/4/24/3","title":"其三"},{"slug":"/cn/1153/4/24/4","title":"其四"}]},{"slug":"/cn/1153/4/25","title":"建霞楼观奕"},{"slug":"/cn/1153/4/26","title":"题画"},{"slug":"/cn/1153/4/27","title":"题碧桃为新婚"},{"slug":"/cn/1153/4/28","title":"送匡云上人归卢山"},{"slug":"/cn/1153/4/29","title":"畹兰二章和黄逢永（有引）","child":[{"slug":"/cn/1153/4/29/1","title":"其一"},{"slug":"/cn/1153/4/29/2","title":"其二"}]},{"slug":"/cn/1153/4/30","title":"塞上曲"},{"slug":"/cn/1153/4/31","title":"陈治父送至峡山留别"},{"slug":"/cn/1153/4/32","title":"厓门吊古"},{"slug":"/cn/1153/4/33","title":"送冯别驾赴周府"},{"slug":"/cn/1153/4/34","title":"湖上作","child":[{"slug":"/cn/1153/4/34/1","title":"其一"},{"slug":"/cn/1153/4/34/2","title":"其二"}]},{"slug":"/cn/1153/4/35","title":"木棉花歌","child":[{"slug":"/cn/1153/4/35/1","title":"其一"},{"slug":"/cn/1153/4/35/2","title":"其二"},{"slug":"/cn/1153/4/35/3","title":"其三"},{"slug":"/cn/1153/4/35/4","title":"其四"},{"slug":"/cn/1153/4/35/5","title":"其五"}]},{"slug":"/cn/1153/4/36","title":"初夏口占","child":[{"slug":"/cn/1153/4/36/1","title":"其一"},{"slug":"/cn/1153/4/36/2","title":"其二"},{"slug":"/cn/1153/4/36/3","title":"其三"},{"slug":"/cn/1153/4/36/4","title":"其四"},{"slug":"/cn/1153/4/36/5","title":"其五"},{"slug":"/cn/1153/4/36/6","title":"其六"},{"slug":"/cn/1153/4/36/7","title":"其七"},{"slug":"/cn/1153/4/36/8","title":"其八"},{"slug":"/cn/1153/4/36/9","title":"其九"},{"slug":"/cn/1153/4/36/10","title":"其十"}]}]},{"slug":"/cn/1153/5","title":"五言排律","child":[{"slug":"/cn/1153/5/1","title":"咏水灯"},{"slug":"/cn/1153/5/2","title":"送幻公"},{"slug":"/cn/1153/5/3","title":"渡羚羊峡"},{"slug":"/cn/1153/5/4","title":"自题水西别业"},{"slug":"/cn/1153/5/5","title":"送方仲玉还莆"},{"slug":"/cn/1153/5/6","title":"净社分赋得千佛塔限三肴"},{"slug":"/cn/1153/5/7","title":"杨元孺都督移镇狼山招集海珠寺即席赠别①"},{"slug":"/cn/1153/5/8","title":"白云纪游同陈冲师郑蟾林万伯文用壁间韵"}]},{"slug":"/cn/1153/6","title":"七言排律　送袁元素中丞乞终制南还"},{"slug":"/cn/1153/7","title":"古风","child":[{"slug":"/cn/1153/7/1","title":"短歌行"},{"slug":"/cn/1153/7/2","title":"远将归"},{"slug":"/cn/1153/7/3","title":"寄远曲"},{"slug":"/cn/1153/7/4","title":"乌夜啼"},{"slug":"/cn/1153/7/5","title":"白马篇"},{"slug":"/cn/1153/7/6","title":"珠江曲","child":[{"slug":"/cn/1153/7/6/1","title":"其一"},{"slug":"/cn/1153/7/6/2","title":"其二"},{"slug":"/cn/1153/7/6/3","title":"其三"},{"slug":"/cn/1153/7/6/4","title":"其四"}]},{"slug":"/cn/1153/7/7","title":"美人独睡歌"},{"slug":"/cn/1153/7/8","title":"新婚乐赠刘萧郎"},{"slug":"/cn/1153/7/9","title":"青楼曲戏代酉校书寄徐元度"},{"slug":"/cn/1153/7/10","title":"咏怀十首","child":[{"slug":"/cn/1153/7/10/1","title":"其一"},{"slug":"/cn/1153/7/10/2","title":"其二"},{"slug":"/cn/1153/7/10/3","title":"其三"},{"slug":"/cn/1153/7/10/4","title":"其四"},{"slug":"/cn/1153/7/10/5","title":"其五"},{"slug":"/cn/1153/7/10/6","title":"其六"},{"slug":"/cn/1153/7/10/7","title":"其七"},{"slug":"/cn/1153/7/10/8","title":"其八"},{"slug":"/cn/1153/7/10/9","title":"其九"},{"slug":"/cn/1153/7/10/10","title":"其十"}]},{"slug":"/cn/1153/7/11","title":"寄陈来献"},{"slug":"/cn/1153/7/12","title":"送李伯襄","child":[{"slug":"/cn/1153/7/12/1","title":"其一"},{"slug":"/cn/1153/7/12/2","title":"其二"}]},{"slug":"/cn/1153/7/13","title":"送张桓孺"},{"slug":"/cn/1153/7/14","title":"送黄逢永"},{"slug":"/cn/1153/7/15","title":"送卢玄明"},{"slug":"/cn/1153/7/16","title":"西行","child":[{"slug":"/cn/1153/7/16/1","title":"其一"},{"slug":"/cn/1153/7/16/2","title":"其二"}]},{"slug":"/cn/1153/7/17","title":"陟巘"},{"slug":"/cn/1153/7/18","title":"寄邓玄度少参楚中"},{"slug":"/cn/1153/7/19","title":"题蓼水居赠黎缜之"},{"slug":"/cn/1153/7/20","title":"立秋日欧子建崔季嚜过集"},{"slug":"/cn/1153/7/21","title":"送欧子建"},{"slug":"/cn/1153/7/22","title":"集卢玄明赡鹤楼分赋"},{"slug":"/cn/1153/7/23","title":"峡口望月"},{"slug":"/cn/1153/7/24","title":"秋夜听邻舟美人琵琶"},{"slug":"/cn/1153/7/25","title":"梁明府席上咏文木盘二首","child":[{"slug":"/cn/1153/7/25/1","title":"其一"},{"slug":"/cn/1153/7/25/2","title":"其二"}]},{"slug":"/cn/1153/7/26","title":"送郡侯罗老师入觐"},{"slug":"/cn/1153/7/27","title":"过罗幼良溪上草堂留题"},{"slug":"/cn/1153/7/28","title":"咏水灯"},{"slug":"/cn/1153/7/29","title":"咏红梅"},{"slug":"/cn/1153/7/30","title":"雁声篇"},{"slug":"/cn/1153/7/31","title":"秋日作"},{"slug":"/cn/1153/7/32","title":"忆旧游寄张约之"},{"slug":"/cn/1153/7/33","title":"山中寄答马伯超"},{"slug":"/cn/1153/7/34","title":"题黄与东鹪鹩园"},{"slug":"/cn/1153/7/35","title":"走哭欧子建尊人"},{"slug":"/cn/1153/7/36","title":"寿陈参戎"},{"slug":"/cn/1153/7/37","title":"云间康季脩素豪于饮王大将军曾为作康山人拜酒歌顷从余饮乃不任涓滴戏有此赠"},{"slug":"/cn/1153/7/38","title":"送汪仲嘉还新都"},{"slug":"/cn/1153/7/39","title":"送韩绪仲太史还朝"},{"slug":"/cn/1153/7/40","title":"送朱季美"},{"slug":"/cn/1153/7/41","title":"为韩宾仲悼亡"},{"slug":"/cn/1153/7/42","title":"赠董参戎"},{"slug":"/cn/1153/7/43","title":"塞上曲"},{"slug":"/cn/1153/7/44","title":"邓玄度观察席上分赋得宝剑篇"},{"slug":"/cn/1153/7/45","title":"送方士昭"},{"slug":"/cn/1153/7/46","title":"赠卢无献"},{"slug":"/cn/1153/7/47","title":"题飞节淩霄图"},{"slug":"/cn/1153/7/48","title":"月华诗为郭明府赋"},{"slug":"/cn/1153/7/49","title":"至日同邓玄度林垂之陈来献梁伯阇袁楚生诸公集周彦昆龙洲草堂"},{"slug":"/cn/1153/7/50","title":"咏竹寿邓玄度"},{"slug":"/cn/1153/7/51","title":"钟太守举子"},{"slug":"/cn/1153/7/52","title":"宝剑篇送梁非馨"},{"slug":"/cn/1153/7/53","title":"会冢行美侍郎田公及义士王潜父也"},{"slug":"/cn/1153/7/54","title":"题李伯开小像"},{"slug":"/cn/1153/7/55","title":"留别梁君南"},{"slug":"/cn/1153/7/56","title":"春草"},{"slug":"/cn/1153/7/57","title":"山厨"},{"slug":"/cn/1153/7/58","title":"无题","child":[{"slug":"/cn/1153/7/58/1","title":"其一"},{"slug":"/cn/1153/7/58/2","title":"其二"}]},{"slug":"/cn/1153/7/59","title":"游罗浮留别诸同好"},{"slug":"/cn/1153/7/60","title":"赋得江清月近人"},{"slug":"/cn/1153/7/61","title":"明霞篇"},{"slug":"/cn/1153/7/62","title":"登书云台怀韩寅仲兼赠禹宝"},{"slug":"/cn/1153/7/63","title":"始渡罗阳水历诸峰①"},{"slug":"/cn/1153/7/64","title":"过朱明洞"},{"slug":"/cn/1153/7/65","title":"秋夜冲虚观听羽人奏乐"},{"slug":"/cn/1153/7/66","title":"过青霞谷"},{"slug":"/cn/1153/7/67","title":"登麻姑台"},{"slug":"/cn/1153/7/68","title":"过石洞临洗耳泉"},{"slug":"/cn/1153/7/69","title":"石洞山居二首","child":[{"slug":"/cn/1153/7/69/1","title":"其一"},{"slug":"/cn/1153/7/69/2","title":"其二"}]},{"slug":"/cn/1153/7/70","title":"怀仙吟"},{"slug":"/cn/1153/7/71","title":"由黄龙洞越大小石楼登飞云顶"},{"slug":"/cn/1153/7/72","title":"飞云顶观日出作"},{"slug":"/cn/1153/7/73","title":"菖蒲涧"},{"slug":"/cn/1153/7/74","title":"水帘洞"},{"slug":"/cn/1153/7/75","title":"游仙诗三首","child":[{"slug":"/cn/1153/7/75/1","title":"其一"},{"slug":"/cn/1153/7/75/2","title":"其二"},{"slug":"/cn/1153/7/75/3","title":"其三"}]},{"slug":"/cn/1153/7/76","title":"杂兴","child":[{"slug":"/cn/1153/7/76/1","title":"其一"},{"slug":"/cn/1153/7/76/2","title":"其二"},{"slug":"/cn/1153/7/76/3","title":"其三"},{"slug":"/cn/1153/7/76/4","title":"其四"},{"slug":"/cn/1153/7/76/5","title":"其五"},{"slug":"/cn/1153/7/76/6","title":"其六"},{"slug":"/cn/1153/7/76/7","title":"其七"},{"slug":"/cn/1153/7/76/8","title":"其八"}]},{"slug":"/cn/1153/7/77","title":"清溪"},{"slug":"/cn/1153/7/78","title":"神湖"},{"slug":"/cn/1153/7/79","title":"白莲池"},{"slug":"/cn/1153/7/80","title":"赠同游张桓孺张美之韩煦重韩禹贤"},{"slug":"/cn/1153/7/81","title":"赠唐长卿"},{"slug":"/cn/1153/7/82","title":"寄梁子"},{"slug":"/cn/1153/7/83","title":"寄答新都汪仲嘉"},{"slug":"/cn/1153/7/84","title":"清溪雨后作"},{"slug":"/cn/1153/7/85","title":"罗溪田家作"},{"slug":"/cn/1153/7/86","title":"孤鸿篇寄黎马龙罗集虚"},{"slug":"/cn/1153/7/87","title":"出山识感"},{"slug":"/cn/1153/7/88","title":"上龙门滩同卢原父"},{"slug":"/cn/1153/7/89","title":"苍梧舟中遇霞丽人戏赠"},{"slug":"/cn/1153/7/90","title":"溯府江而西山青水碧应接不暇得诗四首","child":[{"slug":"/cn/1153/7/90/1","title":"其一"},{"slug":"/cn/1153/7/90/2","title":"其二"},{"slug":"/cn/1153/7/90/3","title":"其三"},{"slug":"/cn/1153/7/90/4","title":"其四"}]},{"slug":"/cn/1153/7/91","title":"下雷霹滩"},{"slug":"/cn/1153/7/92","title":"过厂"},{"slug":"/cn/1153/7/93","title":"艳曲为卢一清作"},{"slug":"/cn/1153/7/94","title":"龙头生"},{"slug":"/cn/1153/7/95","title":"白纻四时歌","child":[{"slug":"/cn/1153/7/95/1","title":"其一"},{"slug":"/cn/1153/7/95/2","title":"其二"},{"slug":"/cn/1153/7/95/3","title":"其三"},{"slug":"/cn/1153/7/95/4","title":"其四"}]},{"slug":"/cn/1153/7/96","title":"结客少年场"},{"slug":"/cn/1153/7/97","title":"赠朱惟四读书峡山青歌楼"},{"slug":"/cn/1153/7/98","title":"送方伯谏还闽"},{"slug":"/cn/1153/7/99","title":"秧马歌"},{"slug":"/cn/1153/7/100","title":"从军行"},{"slug":"/cn/1153/7/101","title":"李伯襄招同诸子春泛"},{"slug":"/cn/1153/7/102","title":"题福清八景寿叶师相（取二首）","child":[{"slug":"/cn/1153/7/102/1","title":"其一 三山列翠"},{"slug":"/cn/1153/7/102/2","title":"其二 鳌顶云峰"}]},{"slug":"/cn/1153/7/103","title":"作霖灵石"},{"slug":"/cn/1153/7/104","title":"驾海仙坛"},{"slug":"/cn/1153/7/105","title":"送马孝廉"},{"slug":"/cn/1153/7/106","title":"送区启图"},{"slug":"/cn/1153/7/107","title":"送李伯襄"},{"slug":"/cn/1153/7/108","title":"送黄逢永读书玉溪"},{"slug":"/cn/1153/7/109","title":"题绮绚堂"},{"slug":"/cn/1153/7/110","title":"送陈道生北游"},{"slug":"/cn/1153/7/111","title":"题笑忙园"},{"slug":"/cn/1153/7/112","title":"石楼老人歌寿梁明府"},{"slug":"/cn/1153/7/113","title":"赋得分影剑为区母寿"},{"slug":"/cn/1153/7/114","title":"送黄仕明宫谕"},{"slug":"/cn/1153/7/115","title":"赠九英校书"},{"slug":"/cn/1153/7/116","title":"寿梁无畸尊人少鸾先生"},{"slug":"/cn/1153/7/117","title":"城西水亭放歌送别熊羽人"},{"slug":"/cn/1153/7/118","title":"送何伯良"},{"slug":"/cn/1153/7/119","title":"书所感"},{"slug":"/cn/1153/7/120","title":"送韩孟郁"},{"slug":"/cn/1153/7/121","title":"题群仙拱寿图赠卢封君"},{"slug":"/cn/1153/7/122","title":"送韩寅仲"},{"slug":"/cn/1153/7/123","title":"闻杨都督父子死播事甚烈诗以挽之"},{"slug":"/cn/1153/7/124","title":"哭侄仲良"},{"slug":"/cn/1153/7/125","title":"友人区启图黎孺旬黄逢永黎美周邝湛若诸子念予远行日过握别酬谢二章","child":[{"slug":"/cn/1153/7/125/1","title":"其一"},{"slug":"/cn/1153/7/125/2","title":"其二"}]},{"slug":"/cn/1153/7/126","title":"留别陆叔度二章","child":[{"slug":"/cn/1153/7/126/1","title":"其一"},{"slug":"/cn/1153/7/126/2","title":"其二"}]},{"slug":"/cn/1153/7/127","title":"经漂母祠及淮阴祠"},{"slug":"/cn/1153/7/128","title":"清明述怀二首","child":[{"slug":"/cn/1153/7/128/1","title":"其一"},{"slug":"/cn/1153/7/128/2","title":"其二"}]},{"slug":"/cn/1153/7/129","title":"望湖亭怀马龙"},{"slug":"/cn/1153/7/130","title":"九日临淮侯李玄素招同阮集之朱白石江遗民吴栗仲田卫公何丕承方圣羽王禹开方尔止方密之梁非馨集松筠阁同用远之"},{"slug":"/cn/1153/7/131","title":"登石头城同李伯襄宫詹"},{"slug":"/cn/1153/7/132","title":"汪士衡中秘招同阮光禄黄符卿诸公集寤园"},{"slug":"/cn/1153/7/133","title":"听邻舟美人琵琶"},{"slug":"/cn/1153/7/134","title":"啸楼诗自选后集怀陈燮伯却寄"},{"slug":"/cn/1153/7/135","title":"吊武烈女①"},{"slug":"/cn/1153/7/136","title":"赠新都孙子真"},{"slug":"/cn/1153/7/137","title":"友人黄逢永尝言晚下清溪遥望西崖诸峰如青纱帐中十数美人探头窥客予酷爱其语壬戌冬溯漓江而西适与此景会为赋是诗"},{"slug":"/cn/1153/7/138","title":"观射呈袁仲符给谏"},{"slug":"/cn/1153/7/139","title":"妾薄命戏似陈伯燮"},{"slug":"/cn/1153/7/140","title":"留别卢原父"},{"slug":"/cn/1153/7/141","title":"题峡江楼赠林六长"},{"slug":"/cn/1153/7/142","title":"燕子楼"},{"slug":"/cn/1153/7/143","title":"舟夜听李文炳弹琵琶"},{"slug":"/cn/1153/7/144","title":"题芝园赠吴尔达通参"},{"slug":"/cn/1153/7/145","title":"初发珠江"},{"slug":"/cn/1153/7/146","title":"江上望陈集生放还不值却寄"},{"slug":"/cn/1153/7/147","title":"古意","child":[{"slug":"/cn/1153/7/147/1","title":"其一"},{"slug":"/cn/1153/7/147/2","title":"其二"},{"slug":"/cn/1153/8/150/4","title":"其二"},{"slug":"/cn/1153/8/150/5","title":"其三"},{"slug":"/cn/1153/8/150/6","title":"其四"}]},{"slug":"/cn/1153/7/148","title":"柬罗幼良"},{"slug":"/cn/1153/7/149","title":"送张山人归始安兼寄汪伯耳"},{"slug":"/cn/1153/7/150","title":"送黎遂球公车北上"}]},{"slug":"/cn/1153/8","title":"词　采莲曲四首"},{"slug":"/cn/1153/9","title":"六言诗","child":[{"slug":"/cn/1153/9/1","title":"水西春日","child":[{"slug":"/cn/1153/9/1/1","title":"其一"},{"slug":"/cn/1153/9/1/2","title":"其二"},{"slug":"/cn/1153/9/1/3","title":"其三"},{"slug":"/cn/1153/9/1/4","title":"其四"}]},{"slug":"/cn/1153/9/2","title":"水西秋日","child":[{"slug":"/cn/1153/9/2/1","title":"其一"},{"slug":"/cn/1153/9/2/2","title":"其二"}]},{"slug":"/cn/1153/9/3","title":"题徐元祥清槐居","child":[{"slug":"/cn/1153/9/3/1","title":"其一"},{"slug":"/cn/1153/9/3/2","title":"其二"}]}]}]}