{"slug":"/cn/695","title":"王文恪公笔记 - (明)王鏊撰","child":[{"slug":"/cn/695/1","title":"宋学士"},{"slug":"/cn/695/2","title":"王行"},{"slug":"/cn/695/3","title":"李征臣"},{"slug":"/cn/695/4","title":"詹徽"},{"slug":"/cn/695/5","title":"姚广孝"},{"slug":"/cn/695/6","title":"耿清"},{"slug":"/cn/695/7","title":"王朴"},{"slug":"/cn/695/8","title":"恩张"},{"slug":"/cn/695/9","title":"王璋"},{"slug":"/cn/695/10","title":"建文"},{"slug":"/cn/695/11","title":"铁布政二女诗"},{"slug":"/cn/695/12","title":"平都司"},{"slug":"/cn/695/13","title":"王府尹"},{"slug":"/cn/695/14","title":"皇甫仲和"},{"slug":"/cn/695/15","title":"王振"},{"slug":"/cn/695/16","title":"陈继"},{"slug":"/cn/695/17","title":"胡濙"},{"slug":"/cn/695/18","title":"薛瑄"},{"slug":"/cn/695/19","title":"王翱"},{"slug":"/cn/695/20","title":"李贤"},{"slug":"/cn/695/21","title":"万安"},{"slug":"/cn/695/22","title":"李秉"},{"slug":"/cn/695/23","title":"王李不同"},{"slug":"/cn/695/24","title":"刘铉"},{"slug":"/cn/695/25","title":"钱溥"},{"slug":"/cn/695/26","title":"陈文"},{"slug":"/cn/695/27","title":"景帝"},{"slug":"/cn/695/28","title":"张益"},{"slug":"/cn/695/29","title":"冯瑶"},{"slug":"/cn/695/30","title":"怀恩"},{"slug":"/cn/695/31","title":"梁芳"},{"slug":"/cn/695/32","title":"门达"},{"slug":"/cn/695/33","title":"王宾"},{"slug":"/cn/695/34","title":"盛启东"},{"slug":"/cn/695/35","title":"丘浚"},{"slug":"/cn/695/36","title":"徐溥"},{"slug":"/cn/695/37","title":"汤鼐"},{"slug":"/cn/695/38","title":"吴宽谢迁"},{"slug":"/cn/695/39","title":"吴惠"},{"slug":"/cn/695/40","title":"李广"},{"slug":"/cn/695/41","title":"赵风子"},{"slug":"/cn/695/42","title":"灾异"},{"slug":"/cn/695/43","title":"财赋之数"},{"slug":"/cn/695/44","title":"财用之数"},{"slug":"/cn/695/45","title":"每年出数"},{"slug":"/cn/695/46","title":"天下粮数"}]}