{"slug":"/cn/608","title":"石匮书后集 - (明清)张岱","child":[{"slug":"/cn/608/1","title":"卷一 烈皇帝本纪"},{"slug":"/cn/608/2","title":"卷二 烈皇后本纪"},{"slug":"/cn/608/3","title":"卷三 太子本纪"},{"slug":"/cn/608/4","title":"卷四 烈二王世家"},{"slug":"/cn/608/5","title":"卷五 明末五王世家（有总论）"},{"slug":"/cn/608/6","title":"卷六 戚畹世家"},{"slug":"/cn/608/7","title":"卷七 朱燮元列传"},{"slug":"/cn/608/8","title":"卷八 孙承宗（鹿善继）、贺逢圣、吕维祺、姜曰广列传"},{"slug":"/cn/608/9","title":"卷九 文震孟、姚希孟列传"},{"slug":"/cn/608/10","title":"卷十 毛文龙列传"},{"slug":"/cn/608/11","title":"卷十一 袁崇焕列传"},{"slug":"/cn/608/12","title":"卷十二 周延儒、杨嗣昌、温体仁列传（阙）"},{"slug":"/cn/608/13","title":"卷十三 蒋德璟、黄景昉、吴甡列传"},{"slug":"/cn/608/14","title":"卷十四 流寇死事诸臣列传"},{"slug":"/cn/608/15","title":"卷十五 卢象升列传"},{"slug":"/cn/608/16","title":"卷十六 流寇死战诸臣列传（有总论）"},{"slug":"/cn/608/17","title":"卷十七 朱之冯、卫景瑗、蔡懋德列传"},{"slug":"/cn/608/18","title":"卷十八 曹文诏、贺人龙列传"},{"slug":"/cn/608/19","title":"卷十九 陆梦龙列传"},{"slug":"/cn/608/20","title":"卷二十 甲申死难列传（有总论）"},{"slug":"/cn/608/21","title":"卷二十一 勋戚殉难列传"},{"slug":"/cn/608/22","title":"卷二十二 倪元璐列传"},{"slug":"/cn/608/23","title":"卷二十三 乡绅死义列传（有总论）"},{"slug":"/cn/608/24","title":"卷二十四 史可法列传"},{"slug":"/cn/608/25","title":"卷二十五 左良玉列传"},{"slug":"/cn/608/26","title":"卷二十六 钱谦益、王铎列传（阙）"},{"slug":"/cn/608/27","title":"卷二十七 洪承畴、冯铨列传（阙）"},{"slug":"/cn/608/28","title":"卷二十八 死义诸臣列传"},{"slug":"/cn/608/29","title":"卷二十九 左懋第列传"},{"slug":"/cn/608/30","title":"卷三十 郑芝龙列传（阙）"},{"slug":"/cn/608/31","title":"卷三十一 吴三桂列传（阙）"},{"slug":"/cn/608/32","title":"卷三十二 乙酉殉难列传（有总论）"},{"slug":"/cn/608/33","title":"卷三十三 凌駉列传"},{"slug":"/cn/608/34","title":"卷三十四 江南死义列传"},{"slug":"/cn/608/35","title":"卷三十五 夏之旭、满之章、何光显列传"},{"slug":"/cn/608/36","title":"卷三十六 刘宗周、祁彪佳列传"},{"slug":"/cn/608/37","title":"卷三十七 黄道周、金声列传"},{"slug":"/cn/608/38","title":"卷三十八 黄得功列传（附刘泽清、高杰、刘良佐）"},{"slug":"/cn/608/39","title":"卷三十九 丙戌殉难列传（有总论）"},{"slug":"/cn/608/40","title":"卷四十 张国维列传"},{"slug":"/cn/608/41","title":"卷四十一 朱大典列传（附吴邦璿、何武）"},{"slug":"/cn/608/42","title":"卷四十二 王之仁、张鹏翼列传"},{"slug":"/cn/608/43","title":"卷四十三 张春列传（阙）"},{"slug":"/cn/608/44","title":"卷四十四 熊汝霖、孙嘉绩、钱肃乐、郑遵谦列传（阙）"},{"slug":"/cn/608/45","title":"卷四十五 余煌、陈函辉、陈潜夫列传"},{"slug":"/cn/608/46","title":"卷四十六 江右死义列传"},{"slug":"/cn/608/47","title":"卷四十七 堵胤锡、何腾蛟列传"},{"slug":"/cn/608/48","title":"卷四十八 马士英、阮大铖列传（附方国安）"},{"slug":"/cn/608/49","title":"卷四十九 闽虔两广死义列传"},{"slug":"/cn/608/50","title":"卷五十 辛卯殉难列传（有总论）"},{"slug":"/cn/608/51","title":"卷五十一 黄斌卿、张名振、王朝先、阮俊列传"},{"slug":"/cn/608/52","title":"卷五十二 瞿式耜列传"},{"slug":"/cn/608/53","title":"卷五十三 陶仰用、朱旻如、蒋武烈、廖应登列传"},{"slug":"/cn/608/54","title":"卷五十四 张煌言列传（阙）"},{"slug":"/cn/608/55","title":"卷五十五 甘辉列传（阙）"},{"slug":"/cn/608/56","title":"卷五十六 孝子列传"},{"slug":"/cn/608/57","title":"卷五十七 义人列传"},{"slug":"/cn/608/58","title":"卷五十八 文苑列传"},{"slug":"/cn/608/59","title":"卷五十九 列女列传"},{"slug":"/cn/608/60","title":"卷六十 妙艺列传"},{"slug":"/cn/608/61","title":"卷六十一 宦者列传"},{"slug":"/cn/608/62","title":"卷六十二 中国群盗列传（有总论）"},{"slug":"/cn/608/63","title":"卷六十三 盗贼列传"}]}