{"slug":"/cn/829","title":"夏天的玫瑰 - 史铁生","child":[{"slug":"/cn/829/1","title":"法学教授及其夫人","open":true},{"slug":"/cn/829/2","title":"午餐半小时","open":true},{"slug":"/cn/829/3","title":"没有太阳的角落","open":true},{"slug":"/cn/829/4","title":"“傻人”的希望","open":true},{"slug":"/cn/829/5","title":"黑黑","open":true},{"slug":"/cn/829/6","title":"小小说四篇","open":true},{"slug":"/cn/829/7","title":"巷口老树下","open":true},{"slug":"/cn/829/8","title":"夏天的玫瑰","open":true},{"slug":"/cn/829/9","title":"老人","open":true},{"slug":"/cn/829/10","title":"奶奶的星星","open":true},{"slug":"/cn/829/11","title":"来到人间","open":true},{"slug":"/cn/829/12","title":"命若琴弦","open":true},{"slug":"/cn/829/13","title":"我之舞","open":true},{"slug":"/cn/829/14","title":"小说三篇","open":true},{"slug":"/cn/829/15","title":"一种谜语的几种简单的猜法","open":true},{"slug":"/cn/829/16","title":"钟声","open":true},{"slug":"/cn/829/17","title":"别人","open":true},{"slug":"/cn/829/18","title":"老屋小记","open":true},{"slug":"/cn/829/19","title":"死国幻记","open":true},{"slug":"/cn/829/20","title":"两个故事","open":true},{"slug":"/cn/829/21","title":"小小说七篇","open":true}]}